pathbuster/__init__.py
pathbuster/pathbuster.py
pathbuster/classes/config.py
pathbuster/classes/response.py
pathbuster/utils/common.py
pathbuster-0.3.0.dist-info/METADATA
pathbuster-0.3.0.dist-info/WHEEL
pathbuster-0.3.0.dist-info/entry_points.txt
pathbuster-0.3.0.dist-info/licenses/LICENSE
pathbuster-0.3.0.dist-info/RECORD
