Metadata-Version: 2.1
Name: pathbuster
Version: 0.3.0
Summary: PathBuster - multiple hosts Web path scanner
Project-URL: Homepage, https://github.com/rivalsec/pathbuster
Project-URL: Bug Tracker, https://github.com/rivalsec/pathbuster/issues
Author: Vladimir Sopernikov
License-File: LICENSE
Classifier: License :: OSI Approved :: MIT License
Classifier: Operating System :: OS Independent
Classifier: Programming Language :: Python :: 3
Requires-Python: >=3.7
Requires-Dist: requests
